django_emojiwatch-0.0.8.dist-info/METADATA
django_emojiwatch-0.0.8.dist-info/RECORD
django_emojiwatch-0.0.8.dist-info/WHEEL
django_emojiwatch-0.0.8.dist-info/top_level.txt
emojiwatch/__init__.py
emojiwatch/admin.py
emojiwatch/apps.py
emojiwatch/models.py
emojiwatch/urls.py
emojiwatch/version.py
emojiwatch/views.py
emojiwatch/migrations/0001_initial.py
emojiwatch/migrations/__init__.py
emojiwatch/static/emojiwatch/images/emojiwatch.png
emojiwatch/templates/admin/emojiwatch/change_form.html
