Metadata-Version: 1.1
Name: django-emojiwatch
Version: 0.0.8
Summary: Bare bones Slack app for posting custom emoji updates to a designated channel
Home-page: https://django-emojiwatch.readthedocs.org/en/v0.0.8/
Author: Matt Bogosian
Author-email: matt@bogosian.net
License: MIT License
Platform: UNKNOWN
Classifier: Topic :: Communications :: Chat
Classifier: Topic :: Office/Business :: Groupware
Classifier: Development Status :: 3 - Alpha
Classifier: Framework :: Django
Classifier: Framework :: Django :: 1.8
Classifier: Framework :: Django :: 1.11
Classifier: Framework :: Django :: 2.0
Classifier: Intended Audience :: System Administrators
Classifier: License :: OSI Approved :: MIT License
Classifier: Operating System :: OS Independent
Classifier: Programming Language :: Python
Classifier: Programming Language :: Python :: 2.7
Classifier: Programming Language :: Python :: 3.4
Classifier: Programming Language :: Python :: 3.5
Classifier: Programming Language :: Python :: 3.6
Classifier: Programming Language :: Python :: Implementation :: CPython
Classifier: Programming Language :: Python :: Implementation :: PyPy
